<Properties StartupConfiguration="{06ABAAEE-9F5C-4E06-8BE3-CD984E918C0F}|https">
  <MonoDevelop.Ide.Workspace ActiveConfiguration="Debug" />
  <MonoDevelop.Ide.Workbench ActiveDocument="Controllers/ProductsController.cs">
    <Files>
      <File FileName="Program.cs" />
      <File FileName="Models/Products.cs" />
      <File FileName="Controllers/ProductsController.cs" Line="25" Column="10" />
      <File FileName="appsettings.json" />
    </Files>
    <Pads>
      <Pad Id="ProjectPad">
        <State name="__root__">
          <Node name="ApiDemo" expanded="True">
            <Node name="ApiDemo" expanded="True">
              <Node name="Controllers" expanded="True">
                <Node name="ProductsController.cs" selected="True" />
              </Node>
              <Node name="Models" expanded="True" />
            </Node>
          </Node>
        </State>
      </Pad>
    </Pads>
  </MonoDevelop.Ide.Workbench>
  <MonoDevelop.Ide.ItemProperties.ApiDemo PreferredExecutionTarget="/Applications/Google Chrome.app" FirstBuild="True" />
  <MonoDevelop.Ide.DebuggingService.Breakpoints>
    <BreakpointStore />
  </MonoDevelop.Ide.DebuggingService.Breakpoints>
  <MonoDevelop.Ide.DebuggingService.PinnedWatches />
  <MultiItemStartupConfigurations />
</Properties>